munity/__init__.py
munity/admin.py
munity/apps.py
munity/models.py
munity/rest.py
munity/tests.py
munity/utils.py
munity/views.py
munity/authenticate/views.py
munity/authorization/__init__.py
munity/authorization/admin.py
munity/authorization/apps.py
munity/authorization/models.py
munity/authorization/permissions.py
munity/authorization/tests.py
munity/authorization/views.py
munity/authorization/management/commands/__init__.py
munity/authorization/management/commands/initiate_default_authorization.py
munity/authorization/migrations/0001_initial.py
munity/authorization/migrations/0002_auto_20211017_2017.py
munity/authorization/migrations/0003_auto_20211017_2031.py
munity/authorization/migrations/0004_auto_20211017_2104.py
munity/authorization/migrations/0005_auto_20211017_2105.py
munity/authorization/migrations/0006_auto_20211019_0904.py
munity/authorization/migrations/0007_auto_20211202_2134.py
munity/authorization/migrations/0008_auto_20211215_1622.py
munity/authorization/migrations/0009_auto_20220403_1426.py
munity/authorization/migrations/__init__.py
munity/files/__init__.py
munity/files/apps.py
munity/files/models.py
munity/files/views.py
munity/files/migrations/0001_initial.py
munity/files/migrations/0002_file_generic_groups.py
munity/files/migrations/0003_file_disabled.py
munity/files/migrations/0004_file_informations.py
munity/files/migrations/__init__.py
munity/generic_groups/__init__.py
munity/generic_groups/admin.py
munity/generic_groups/apps.py
munity/generic_groups/models.py
munity/generic_groups/views.py
munity/generic_groups/migrations/0001_initial.py
munity/generic_groups/migrations/0002_genericgroup_related_workspace.py
munity/generic_groups/migrations/0003_rename_related_workspace_genericgroup_workspace.py
munity/generic_groups/migrations/0004_remove_genericgroup_workspace.py
munity/generic_groups/migrations/0005_genericgroup_workspace.py
munity/generic_groups/migrations/0006_alter_genericgroup_workspace.py
munityapps-0.1.61.dist-info/LICENSE
munityapps-0.1.61.dist-info/METADATA
munityapps-0.1.61.dist-info/WHEEL
munityapps-0.1.61.dist-info/top_level.txt
munityapps-0.1.61.dist-info/RECORD
