Metadata-Version: 2.1
Name: munityapps
Version: 0.1.61
Summary: API for munity project
Home-page: https://munityapps.com
Author: Cyril ALFARO
Author-email: cyril@munityapps.com
License: UNKNOWN
Project-URL: Bug Tracker, https://github.com/munityapps/munity
Platform: UNKNOWN
Classifier: Programming Language :: Python :: 3
Classifier: License :: OSI Approved :: MIT License
Classifier: Operating System :: OS Independent
Requires-Python: >=3.9
License-File: LICENSE
